my_library/__init__.py
my_library/magic_effects.py
pymagic_hm-0.1.dist-info/licenses/LICENSE
pymagic_hm-0.1.dist-info/METADATA
pymagic_hm-0.1.dist-info/WHEEL
pymagic_hm-0.1.dist-info/top_level.txt
pymagic_hm-0.1.dist-info/RECORD
