Metadata-Version: 2.4
Name: pymagic_HM
Version: 0.1
Summary: A library for creating magic effects in games.
Author: Houda Izem
Author-email: houdaizem166@gmail.com
Classifier: Programming Language :: Python :: 3
Classifier: License :: OSI Approved :: MIT License
Classifier: Operating System :: OS Independent
License-File: LICENSE
Requires-Dist: pygame
Dynamic: author
Dynamic: author-email
Dynamic: classifier
Dynamic: description
Dynamic: description-content-type
Dynamic: license-file
Dynamic: requires-dist
Dynamic: summary
